flow_forge/__init__.py
flow_forge/__main__.py
flow_forge/py.typed
flow_forge-0.0.0.dist-info/entry_points.txt
flow_forge-0.0.0.dist-info/LICENSE
flow_forge-0.0.0.dist-info/METADATA
flow_forge-0.0.0.dist-info/WHEEL
flow_forge-0.0.0.dist-info/RECORD
